README.md
setup.py
simpgenalg/__init__.py
simpgenalg/meta.py
simpgenalg.egg-info/PKG-INFO
simpgenalg.egg-info/SOURCES.txt
simpgenalg.egg-info/dependency_links.txt
simpgenalg.egg-info/requires.txt
simpgenalg.egg-info/top_level.txt
simpgenalg/basics/__init__.py
simpgenalg/crossovers/__init__.py
simpgenalg/crossovers/homoonept.py
simpgenalg/crossovers/onept.py
simpgenalg/crossovers/twopt.py
simpgenalg/crossovers/uniform.py
simpgenalg/crossovers/vartwopt.py
simpgenalg/crossovers/basics/__init__.py
simpgenalg/crossovers/basics/bscXov.py
simpgenalg/crossovers/unittests/__init__.py
simpgenalg/evaluators/__init__.py
simpgenalg/evaluators/fxnEval.py
simpgenalg/evaluators/basics/__init__.py
simpgenalg/evaluators/basics/bscEvl.py
simpgenalg/mutations/__init__.py
simpgenalg/mutations/flipbit.py
simpgenalg/mutations/gaussian.py
simpgenalg/mutations/swap.py
simpgenalg/mutations/uniform.py
simpgenalg/mutations/basics/__init__.py
simpgenalg/mutations/basics/bscMut.py
simpgenalg/other/__init__.py
simpgenalg/other/bscCmpnt.py
simpgenalg/other/cstm_logger.py
simpgenalg/other/results.py
simpgenalg/other/tlbx.py
simpgenalg/populations/__init__.py
simpgenalg/populations/fixPop.py
simpgenalg/populations/basics/__init__.py
simpgenalg/populations/basics/bscPop.py
simpgenalg/representations/__init__.py
simpgenalg/representations/binary.py
simpgenalg/representations/floating.py
simpgenalg/representations/messy.py
simpgenalg/representations/proportional.py
simpgenalg/representations/vector.py
simpgenalg/representations/basics/__init__.py
simpgenalg/representations/basics/bscChromo.py
simpgenalg/representations/basics/bscRep.py
simpgenalg/selectors/__init__.py
simpgenalg/selectors/tourn.py
simpgenalg/selectors/basics/__init__.py
simpgenalg/selectors/basics/bsc_slctr.py
simpgenalg/structures/__init__.py
simpgenalg/structures/basics/__init__.py
simpgenalg/structures/basics/bscStruct.py
simpgenalg/structures/generation/__init__.py
simpgenalg/structures/generation/gen_dash_view.py
simpgenalg/structures/generation/gen_rslts.py
simpgenalg/structures/generation/gen_rslts_old.py
simpgenalg/structures/generation/generation.py
simpgenalg/structures/generation/op_app.py
